tap_mixpanel/__init__.py
tap_mixpanel/client.py
tap_mixpanel/discover.py
tap_mixpanel/schema.py
tap_mixpanel/streams.py
tap_mixpanel/sync.py
tap_mixpanel/transform.py
tap_mixpanel/schemas/annotations.json
tap_mixpanel/schemas/cohort_members.json
tap_mixpanel/schemas/cohorts.json
tap_mixpanel/schemas/engage.json
tap_mixpanel/schemas/export.json
tap_mixpanel/schemas/funnels.json
tap_mixpanel/schemas/revenue.json
tests/__init__.py
tests/configuration/__init__.py
tests/configuration/fixtures.py
tests/tap_tester/__init__.py
tests/tap_tester/tap_combined_test.py
tests/tap_tester/test_configuration.py
tests/unittests/__init__.py
tests/unittests/test_medium_client.py
pipelinewise_tap_mixpanel-1.2.0.dist-info/LICENSE
pipelinewise_tap_mixpanel-1.2.0.dist-info/METADATA
pipelinewise_tap_mixpanel-1.2.0.dist-info/WHEEL
pipelinewise_tap_mixpanel-1.2.0.dist-info/entry_points.txt
pipelinewise_tap_mixpanel-1.2.0.dist-info/top_level.txt
pipelinewise_tap_mixpanel-1.2.0.dist-info/RECORD
