Metadata-Version: 2.1
Name: pipelinewise-tap-mixpanel
Version: 1.2.0
Summary: Singer.io tap for extracting data from the mixpanel API - PipelineWise compatible
Home-page: UNKNOWN
Author: jeff.huth@bytecode.io & TransferWise
License: UNKNOWN
Platform: UNKNOWN
Classifier: License :: OSI Approved :: GNU Affero General Public License v3
Classifier: Programming Language :: Python :: 3 :: Only
Requires-Dist: backoff (==1.8.0)
Requires-Dist: requests (==2.22.0)
Requires-Dist: pipelinewise-singer-python (==1.*)
Requires-Dist: jsonlines (==1.2.0)
Provides-Extra: test
Requires-Dist: pytest ; extra == 'test'
Requires-Dist: pylint ; extra == 'test'
Requires-Dist: requests-mock ; extra == 'test'
